scope/__init__.py
scope/emd/__init__.py
scope/emd/emd_energy_spectrum.py
scope/emd/emd_modes.py
scope/emd/emd_noise_conf.py
scope/emd/emd_period_energy.py
scope/emd/emd_trend.py
scope/emd/waveletFunctions.py
scope/fourier/__init__.py
scope/fourier/fit_fourier.py
scope/utils/__init__.py
scope/utils/plot.py
scope_emd-1.0.0.dist-info/licenses/LICENSE
tests/__init__.py
tests/test_emd.py
tests/test_fit_fourier.py
scope_emd-1.0.0.dist-info/METADATA
scope_emd-1.0.0.dist-info/WHEEL
scope_emd-1.0.0.dist-info/top_level.txt
scope_emd-1.0.0.dist-info/RECORD
