Metadata-Version: 2.4
Name: scope-emd
Version: 1.0.0
Summary: scope is the Python-based package for detecting oscillatory                  signals in observational or experimental time series with the                 EMD technique and assessing their statistical significance vs.                 power-law distributed background noise.
Home-page: https://github.com/Warwick-Solar/scope
Author: Dmitrii Kolotkov, Weijie Gu, Sergey Belov, Valery Nakariakov
Author-email: Sergey.Belov@warwick.ac.uk
Classifier: Programming Language :: Python :: 3
Classifier: License :: OSI Approved :: Apache Software License
Classifier: Operating System :: OS Independent
Requires-Python: >=3.8
License-File: LICENSE
Requires-Dist: colorednoise>=2.2.0
Requires-Dist: emd>=0.7.0
Requires-Dist: numpy>=1.3.0
Requires-Dist: lmfit>=1.3.2
Requires-Dist: tqdm>=4.0.0
Provides-Extra: dev
Requires-Dist: pytest; extra == "dev"
Requires-Dist: coverage; extra == "dev"
Requires-Dist: pytest-cov; extra == "dev"
Dynamic: author
Dynamic: author-email
Dynamic: classifier
Dynamic: description
Dynamic: description-content-type
Dynamic: home-page
Dynamic: license-file
Dynamic: provides-extra
Dynamic: requires-dist
Dynamic: requires-python
Dynamic: summary
